README.md
setup.py
tests/__init__.py
tests/test_youversion.py
youversion/__init__.py
youversion/youversion.py
youversion.egg-info/PKG-INFO
youversion.egg-info/SOURCES.txt
youversion.egg-info/dependency_links.txt
youversion.egg-info/requires.txt
youversion.egg-info/top_level.txt