Metadata-Version: 2.1
Name: youversion
Version: 0.1.0
Summary: YouVersion API Client
Home-page: https://github.com/jyksnw/yv-api-python
Author: Jason Snow
Author-email: jsn.snw@gmail.com
License: Apache License, Version 2.0
Keywords: YouVersion Bible API Client
Platform: UNKNOWN
Classifier: Development Status :: 5 - Production/Stable
Classifier: Intended Audience :: Developers
Classifier: Intended Audience :: Religion
Classifier: Programming Language :: Python :: 3.7
Classifier: Topic :: Religion
Classifier: Topic :: Software Development
Classifier: Topic :: Utilities
Classifier: License :: OSI Approved :: Apache Software License
